cpia/__init__.py
cpia/converter.py
cpia/utils.py
cpia/fsts/avaee.fst
cpia/fsts/expressive.fst
cpia/fsts/generation.fst
cpia/fsts/homophone.fst
cpia/fsts/splitter.fst
cpia/fsts/standard.fst
cpia/streats/convertableStems.txt
cpia/streats/convertableWords.txt
cpia/streats/rule-parts.txt
cpia-2024.7.71.dist-info/LICENSE
cpia-2024.7.71.dist-info/METADATA
cpia-2024.7.71.dist-info/WHEEL
cpia-2024.7.71.dist-info/top_level.txt
cpia-2024.7.71.dist-info/RECORD
