Metadata-Version: 2.1
Name: cpia
Version: 2024.7.71
Summary: Contemporary Persian word analyzer
Author: Davood Heidarpour
Author-email: <chandracar@gmail.com>
Project-URL: Homepage, https://github.com/lingwndr/cpia
Project-URL: Repository, https://github.com/lingwndr/cpia
Keywords: Persian,Farsi,Inflection,Analyzer,Inormal,Formal,Lemmatizer,Converter
Classifier: Intended Audience :: Developers
Classifier: Intended Audience :: Science/Research
Classifier: License :: OSI Approved :: GNU Lesser General Public License v3 (LGPLv3)
Classifier: Programming Language :: Python :: 3.8
Classifier: Programming Language :: Python :: 3.9
Classifier: Programming Language :: Python :: 3.10
Classifier: Programming Language :: Python :: 3.11
Classifier: Programming Language :: Python :: 3.12
Classifier: Topic :: Software Development
Classifier: Topic :: Scientific/Engineering
Classifier: Topic :: Text Processing :: Linguistic
Classifier: Operating System :: Microsoft :: Windows
Classifier: Operating System :: Unix
Classifier: Operating System :: MacOS
License-File: LICENSE
Requires-Dist: fst-lookup >=2024.7.3
